gitlab_data_export/__init__.py
gitlab_data_export/driver.py
gitlab_data_export/util.py
gitlab_data_export/api/__init__.py
gitlab_data_export/api/bigquery.py
gitlab_data_export/api/datastore.py
gitlab_data_export/api/gitlab_export.py
tests/__init__.py
tests/test_driver.py
tests/test_util.py
tests/api/__init__.py
tests/api/test_gitlab_export.py
gitlab_data_export-0.4.1.dist-info/LICENSE.txt
gitlab_data_export-0.4.1.dist-info/METADATA
gitlab_data_export-0.4.1.dist-info/WHEEL
gitlab_data_export-0.4.1.dist-info/entry_points.txt
gitlab_data_export-0.4.1.dist-info/top_level.txt
gitlab_data_export-0.4.1.dist-info/RECORD
