Metadata-Version: 2.2
Name: gitlab_data_export
Version: 0.4.1
Summary: Export GitLab data to external data stores
Home-page: https://gitlab.com/belvederetrading/public/gitlab-data-export
Author: Belvedere Trading
Project-URL: Bug Reports, https://gitlab.com/belvederetrading/public/gitlab-data-export/-/issues
Project-URL: Source, https://gitlab.com/belvederetrading/public/gitlab-data-export
Classifier: Development Status :: 3 - Alpha
Classifier: Intended Audience :: Developers
Classifier: Topic :: Software Development :: Build Tools
Classifier: Topic :: Utilities
Classifier: License :: OSI Approved :: MIT License
Classifier: Programming Language :: Python :: 3
Classifier: Programming Language :: Python :: 3.7
Classifier: Programming Language :: Python :: 3.8
Classifier: Programming Language :: Python :: 3.9
Classifier: Programming Language :: Python :: 3.10
Classifier: Programming Language :: Python :: 3.11
Classifier: Programming Language :: Python :: 3 :: Only
Requires-Python: >=3.7, <4
License-File: LICENSE.txt
Requires-Dist: google-cloud-bigquery<3.20.0,>=3.0.0
Requires-Dist: python-gitlab<4,>=3.0.0
Provides-Extra: dev
Requires-Dist: autopep8; extra == "dev"
Requires-Dist: build; extra == "dev"
Requires-Dist: coverage; extra == "dev"
Requires-Dist: google-auth-stubs; extra == "dev"
Requires-Dist: mypy; extra == "dev"
Requires-Dist: python-dotenv; extra == "dev"
Requires-Dist: twine; extra == "dev"
Dynamic: author
Dynamic: classifier
Dynamic: description
Dynamic: description-content-type
Dynamic: home-page
Dynamic: project-url
Dynamic: provides-extra
Dynamic: requires-dist
Dynamic: requires-python
Dynamic: summary
